rando/__init__.py
rando-0.1.3.dist-info/AUTHORS
rando-0.1.3.dist-info/METADATA
rando-0.1.3.dist-info/WHEEL
rando-0.1.3.dist-info/pbr.json
rando-0.1.3.dist-info/top_level.txt
rando-0.1.3.dist-info/RECORD
