Metadata-Version: 2.1
Name: rando
Version: 0.1.3
Summary: rando is a weighted random generator.
Home-page: https://github.com/demosdemon/leblanc.codes
Author: Brandon LeBlanc
Author-email: brandon@leblanc.codes
License: MIT
Platform: UNKNOWN
Classifier: License :: OSI Approved :: MIT License
Classifier: Programming Language :: Python
Classifier: Programming Language :: Python :: 3
